README.md
setup.py
blink/__init__.py
blink/blink.py
blink_led.egg-info/PKG-INFO
blink_led.egg-info/SOURCES.txt
blink_led.egg-info/dependency_links.txt
blink_led.egg-info/top_level.txt
tests/__init__.py
tests/test_blink.py