Metadata-Version: 1.1
Name: blink-led
Version: 0.1.0
Summary: blinking led
Home-page: https://github.com/CaTaLiS/blink
Author: CaTaLiS
Author-email: catalis.dev@gmail.com
License: UNKNOWN
Keywords: blink led gpio
Platform: UNKNOWN
Classifier: Development Status :: 1 - Planning
Classifier: Topic :: Utilities
